bspy/__init__.py
bspy/_spline_domain.py
bspy/_spline_evaluation.py
bspy/_spline_fitting.py
bspy/_spline_intersection.py
bspy/_spline_milling.py
bspy/_spline_operations.py
bspy/hyperplane.py
bspy/manifold.py
bspy/solid.py
bspy/spline.py
bspy/splineOpenGLFrame.py
bspy/spline_block.py
bspy/viewer.py
bspy-4.4.1.dist-info/licenses/LICENSE
bspy-4.4.1.dist-info/METADATA
bspy-4.4.1.dist-info/WHEEL
bspy-4.4.1.dist-info/top_level.txt
bspy-4.4.1.dist-info/RECORD
