Metadata-Version: 2.4
Name: bspy
Version: 4.4.1
Summary: Library for manipulating and rendering non-uniform B-splines
Home-page: http://github.com/ericbrec/BSpy
Author: Eric Brechner
Author-email: ericbrec@msn.com
License: MIT
Project-URL: Bug Tracker, http://github.com/ericbrec/BSpy/issues
Keywords: bspline,B-spline,nub,solid,solid modeling,geometry,csg,opengl,tkinter
Classifier: License :: OSI Approved :: MIT License
Classifier: Environment :: Win32 (MS Windows)
Classifier: Environment :: Console
Classifier: Intended Audience :: Developers
Classifier: Intended Audience :: Science/Research
Classifier: Topic :: Multimedia :: Graphics
Classifier: Topic :: Multimedia :: Graphics :: 3D Rendering
Classifier: Topic :: Scientific/Engineering
Classifier: Topic :: Scientific/Engineering :: Mathematics
Classifier: Topic :: Scientific/Engineering :: Visualization
Classifier: Topic :: Software Development :: Libraries :: Python Modules
Classifier: Programming Language :: Python :: 3
Classifier: Operating System :: OS Independent
Requires-Python: >=3.0
License-File: LICENSE
Requires-Dist: numpy
Requires-Dist: scipy
Requires-Dist: PyOpenGL
Requires-Dist: pyopengltk
Dynamic: license-file
